LICENSE
README.rst
setup.py
./LICENSE
./README.rst
./__init__.py
./handler.py
./handler8.py
./server.py
./data/copy_license.py
./static/favicon.ico
./static/index.html
./static/reqwest.js
./static/css/app.85ddf991.css
./static/css/chunk-vendors.b79ff3a2.css
./static/fonts/element-icons.535877f5.woff
./static/fonts/element-icons.732389de.ttf
./static/img/calendar-alt.svg
./static/img/calendar-minus.svg
./static/img/calendar.svg
./static/img/cog.svg
./static/img/folder-solid.svg
./static/img/folder.svg
./static/img/logo.a8954ff0.png
./static/img/registered.svg
./static/img/shield-alt.svg
./static/img/tablet-alt.svg
./static/js/app.19b525d6.js
./static/js/chunk-vendors.4afc1da0.js
./test/README.md
./test/generate_expired_license.robot
./test/generate_extra_data_license.robot
./test/generate_machine_license.robot
./test/obfuscate_multiple_entries.robot
./test/obfuscate_one_package.robot
./test/obfuscate_one_script.robot
./test/pack_one_file_bundle.robot
./test/pack_one_file_bundle_with_outer_license.robot
./test/pack_one_folder_bundle.robot
./test/pack_with_data_file.robot
./test/resource.robot
pyarmor_webui.egg-info/PKG-INFO
pyarmor_webui.egg-info/SOURCES.txt
pyarmor_webui.egg-info/dependency_links.txt
pyarmor_webui.egg-info/entry_points.txt
pyarmor_webui.egg-info/requires.txt
pyarmor_webui.egg-info/top_level.txt