Metadata-Version: 2.1
Name: pyarmor-webui
Version: 2.6
Summary: A webui tool used to obfuscate and pack python scripts based on pyarmor
Home-page: https://github.com/dashingsoft/pyarmor-webui
Author: Jondy Zhao
Author-email: pyarmor@163.com
License: MIT License
Platform: UNKNOWN
Classifier: Development Status :: 4 - Beta
Classifier: Intended Audience :: Developers
Classifier: Topic :: Software Development :: Build Tools
Classifier: Topic :: Utilities
Classifier: Topic :: Security
Classifier: Topic :: System :: Software Distribution
Classifier: License :: OSI Approved :: MIT License
Classifier: Operating System :: MacOS
Classifier: Operating System :: Microsoft :: Windows
Classifier: Operating System :: POSIX
Classifier: Programming Language :: Python :: 2
Classifier: Programming Language :: Python :: 3
License-File: LICENSE
